[{"domain": "chartmasters.org", "httpOnly": true, "name": "wordpress_logged_in_4b4411cd135833fdda1e4d56a2e09fa7", "path": "/", "secure": true, "value": "blossom30%7C1625275766%7CfzhgxD2iegPNMnfKuJZLErv7X80pHfEHwurblUF51GR%7Cac4819b72a6517819c25da7a50334c495bd78c2f6418247de970fd6477fea6f9"}, {"domain": "chartmasters.org", "httpOnly": false, "name": "wordpress_test_cookie", "path": "/", "secure": true, "value": "WP+Cookie+check"}, {"domain": "chartmasters.org", "expiry": 1656638963, "httpOnly": false, "name": "viewed_cookie_policy", "path": "/", "secure": false, "value": "yes"}, {"domain": "chartmasters.org", "expiry": 1656638963, "httpOnly": false, "name": "CookieLawInfoConsent", "path": "/", "secure": false, "value": "eyJuZWNlc3NhcnkiOnRydWV9"}, {"domain": ".chartmasters.org", "expiry": 1658798963, "httpOnly": false, "name": "__gads", "path": "/", "secure": false, "value": "ID=4833b382295194b0-228f53f24bc90089:T=1625102963:RT=1625102963:S=ALNI_MbHCCI8NoFnU-MlIL-PXIFglm8DQA"}, {"domain": ".chartmasters.org", "expiry": 1688174965, "httpOnly": false, "name": "_ga", "path": "/", "secure": false, "value": "GA1.2.29087425.1625102963"}, {"domain": ".chartmasters.org", "expiry": 1625189365, "httpOnly": false, "name": "_gid", "path": "/", "secure": false, "value": "GA1.2.1377781552.1625102963"}, {"domain": ".chartmasters.org", "expiry": 1625103023, "httpOnly": false, "name": "_gat_gtag_UA_72533914_1", "path": "/", "secure": false, "value": "1"}, {"domain": "chartmasters.org", "expiry": 1656638963, "httpOnly": false, "name": "cookielawinfo-checkbox-necessary", "path": "/", "secure": false, "value": "yes"}, {"domain": "chartmasters.org", "httpOnly": false, "name": "pmpro_visit", "path": "/", "secure": false, "value": "1"}]