[{"domain": "chartmasters.org", "httpOnly": true, "name": "wordpress_logged_in_4b4411cd135833fdda1e4d56a2e09fa7", "path": "/", "secure": true, "value": "plushy71%7C1625275922%7C9FYcp5h8ltxiBsO1IGVwnpAeu0HGpJ5XEGMjTz3BdZG%7Cc66b69fead50800b44ff434c90886d59e29244649a8e5ccda9b75fba7df4345f"}, {"domain": "chartmasters.org", "httpOnly": false, "name": "wordpress_test_cookie", "path": "/", "secure": true, "value": "WP+Cookie+check"}, {"domain": "chartmasters.org", "expiry": 1656639119, "httpOnly": false, "name": "viewed_cookie_policy", "path": "/", "secure": false, "value": "yes"}, {"domain": "chartmasters.org", "expiry": 1656639119, "httpOnly": false, "name": "CookieLawInfoConsent", "path": "/", "secure": false, "value": "eyJuZWNlc3NhcnkiOnRydWV9"}, {"domain": ".chartmasters.org", "expiry": 1658799119, "httpOnly": false, "name": "__gads", "path": "/", "secure": false, "value": "ID=9fdfbc4923cecffd-225e4ee749c900a7:T=1625103119:RT=1625103119:S=ALNI_Mb0_mjlG1ODo-A5Isd64pGftEdXQQ"}, {"domain": ".chartmasters.org", "expiry": 1625103179, "httpOnly": false, "name": "_gat_gtag_UA_72533914_1", "path": "/", "secure": false, "value": "1"}, {"domain": ".chartmasters.org", "expiry": 1625189521, "httpOnly": false, "name": "_gid", "path": "/", "secure": false, "value": "GA1.2.500606226.1625103119"}, {"domain": ".chartmasters.org", "expiry": 1688175121, "httpOnly": false, "name": "_ga", "path": "/", "secure": false, "value": "GA1.2.318084873.1625103119"}, {"domain": "chartmasters.org", "expiry": 1656639119, "httpOnly": false, "name": "cookielawinfo-checkbox-necessary", "path": "/", "secure": false, "value": "yes"}, {"domain": "chartmasters.org", "httpOnly": false, "name": "pmpro_visit", "path": "/", "secure": false, "value": "1"}]